alpm/__init__.py
alpm/__pycache__/__init__.cpython-313.pyc
alpm/__pycache__/alpm_types.cpython-313.pyc
alpm/__pycache__/type_aliases.cpython-313.pyc
alpm/_native.abi3.so
alpm/_native.pyi
alpm/alpm_srcinfo/__init__.pyi
alpm/alpm_srcinfo/__pycache__/__init__.cpython-313.pyc
alpm/alpm_srcinfo/__pycache__/error.cpython-313.pyc
alpm/alpm_srcinfo/__pycache__/schema.cpython-313.pyc
alpm/alpm_srcinfo/error.pyi
alpm/alpm_srcinfo/schema.pyi
alpm/alpm_srcinfo/source_info/__init__.pyi
alpm/alpm_srcinfo/source_info/__pycache__/__init__.cpython-313.pyc
alpm/alpm_srcinfo/source_info/v1/__init__.pyi
alpm/alpm_srcinfo/source_info/v1/__pycache__/__init__.cpython-313.pyc
alpm/alpm_srcinfo/source_info/v1/__pycache__/merged.cpython-313.pyc
alpm/alpm_srcinfo/source_info/v1/__pycache__/package.cpython-313.pyc
alpm/alpm_srcinfo/source_info/v1/__pycache__/package_base.cpython-313.pyc
alpm/alpm_srcinfo/source_info/v1/merged.pyi
alpm/alpm_srcinfo/source_info/v1/package.pyi
alpm/alpm_srcinfo/source_info/v1/package_base.pyi
alpm/alpm_types.pyi
alpm/py.typed
alpm/type_aliases.py
python_alpm-0.4.0.dist-info/METADATA
python_alpm-0.4.0.dist-info/WHEEL
python_alpm-0.4.0.dist-info/RECORD
