Metadata-Version: 2.4
Name: python-alpm
Version: 0.4.0
Classifier: Intended Audience :: Developers
Classifier: Operating System :: POSIX :: Linux
Classifier: Programming Language :: Python :: Implementation :: CPython
Classifier: Programming Language :: Python :: Implementation :: PyPy
Classifier: Programming Language :: Rust
Summary: Python bindings for the Rust-based ALPM project
Keywords: alpm,archlinux,packaging,srcinfo
Home-Page: https://alpm.archlinux.page
License-Expression: Apache-2.0 OR MIT
Requires-Python: >=3.10
Project-URL: Changelog, https://alpm.archlinux.page/python-alpm/CHANGELOG.html
Project-URL: Documentation, https://alpm.archlinux.page/pdoc/
Project-URL: Homepage, https://alpm.archlinux.page/python-alpm/
Project-URL: Issues, https://gitlab.archlinux.org/archlinux/alpm/alpm/-/issues
Project-URL: Repository, https://gitlab.archlinux.org/archlinux/alpm/alpm
